memcache_lock/__init__.py
memcache_lock/exceptions.py
memcache_lock/uuid_lock.py
memcache_lock-0.0.5.dist-info/LICENSE
memcache_lock-0.0.5.dist-info/METADATA
memcache_lock-0.0.5.dist-info/WHEEL
memcache_lock-0.0.5.dist-info/top_level.txt
memcache_lock-0.0.5.dist-info/RECORD
