Metadata-Version: 2.1
Name: memcache-lock
Version: 0.0.5
Summary: Locking mechanism for Python 2.7 GAE, using memcache
Home-page: https://github.com/linuxpi/memcache_lock
Author: Varun Bansal
Author-email: varunb94@gmail.com
License: MIT
Platform: UNKNOWN
Classifier: Development Status :: 3 - Alpha
Classifier: Intended Audience :: Developers
Classifier: License :: OSI Approved :: MIT License
Classifier: Operating System :: OS Independent
Classifier: Programming Language :: Python :: 2
